README.rst
setup.py
mmb/__init__.py
mmb.egg-info/PKG-INFO
mmb.egg-info/SOURCES.txt
mmb.egg-info/dependency_links.txt
mmb.egg-info/entry_points.txt
mmb.egg-info/requires.txt
mmb.egg-info/top_level.txt