Metadata-Version: 1.1
Name: mmb
Version: 0.0.1
Summary: A backup tool for the elektron monomachine
Home-page: https://github.com/davebrent/mmb
Author: Dave Poulter
Author-email: dapoulter@gmail.com
License: MIT
Keywords: elektron monomachine backup
Platform: any
Classifier: Development Status :: 3 - Alpha
Classifier: Environment :: Console
Classifier: License :: OSI Approved :: MIT License
Classifier: Topic :: Multimedia :: Sound/Audio :: MIDI
Classifier: Topic :: System :: Archiving :: Backup
